<annotation>
  <folder>bbox_annotations</folder>
  <filename>364b.jpg</filename>
  <path>images/364b.jpg</path>
  <vehicle>1</vehicle>
  <camera>1</camera>
  <source>
    <database>Unknown</database>
  </source>
  <size>
    <width>640</width>
    <height>360</height>
    <depth>3</depth>
  </size>
  <segmented>0</segmented>
  <object>
    <name>JB</name>
    <pose>Unspecified</pose>
    <truncated>0</truncated>
    <difficult>0</difficult>
    <bndbox>
      <xmin>2</xmin>
      <ymin>274</ymin>
      <xmax>283</xmax>
      <ymax>355</ymax>
    </bndbox>
  </object>
</annotation>